Workbook

Sheet Synthèse
A1: Synthèse budget partie 1 (HT, indicatif) | B1: Montant
A2: Investissement (CAPEX) | B2: =Investissement!$E$21
A3: Charges d'exploitation 1re année (OPEX) | B3: ='Charges an 1'!$E$11
A4: Coûts internes (RSI + alternant) | B4: =Hypothèses!$B$17*Hypothèses!$B$18+Hypothèses!$B$19*Hypothèses!$B$20
A5: Sous-total | B5: =SUM(B2:B4)
A6: Réserve de contingence | B6: =(B2+B3)*Hypothèses!$B$21
A7: Réserve de management | B7: =(B2+B3)*Hypothèses!$B$22
A8: TOTAL PROJET | B8: =B5+B6+B7
A9: Enveloppe Contexte SAP | B9: =Hypothèses!$B$23
A10: Écart (positif = dépassement) | B10: =B8-B9
A12: Leviers pour revenir dans l'enveloppe
A13: • Passer 'Part de postes reconditionnés' à 40 % (Hypothèses) : économie ≈ 50 k€ + argument RSE
A14: • Basculer l'ERP SaaS dans le budget métier (il relève de la direction, pas de l'infra)
A15: • Location évolutive (DaaS) des portables : transforme ≈ 370 k€ de CAPEX en ≈ 32 €/poste/mois
A16: • Ajuster le nombre de bornes Wi-Fi après l'audit radio
A17: • Étaler les smartphones sur l'an 2 (seulement les 92 HS en an 1)

Sheet Hypothèses
A1: Paramètre | B1: Valeur | C1: Commentaire
A2: Salariés actuels (inventaire 2015) | B2: 450
A3: Croissance annuelle effectifs | B3: 0.05 | C3: Contexte SAP p.11
A4: Stock de spare postes | B4: 0.03 | C4: pannes / arrivées
A5: Prix portable neuf (i5, 16 Go, 512 Go, garantie 3 ans J+1) | B5: 750 | C5: prix indicatif HT
A6: Prix portable reconditionné grade A (garantie 2-3 ans) | B6: 480 | C6: levier GreenIT / budget
A7: Part de postes reconditionnés (0 à 1) | B7: 0 | C7: mettre 0,4 pour le scénario économe
A8: Part du parc renouvelée en année 1 (0 à 1) | B8: 1 | C8: 0,65 = les 300 postes HS + croissance, le reste en an 2
A9: Inclure l'ERP SaaS dans ce budget (1 = oui, 0 = non) | B9: 1 | C9: 0 si porté par le budget métier
A10: Postes fixes administratifs (dock + écran 24") | B10: 150 | C10: admin, direction, chefs de service
A11: Licences M365 E3 (bureautique complète) | B11: 150 | C11: admin, direction, CSE, psy
A12: Licences M365 F3 (terrain, Office web/mobile) | B12: 300 | C12: éducateurs, mandataires
A13: Prix M365 E3 / utilisateur / mois | B13: 36 | C13: indicatif HT
A14: Prix M365 F3 / utilisateur / mois | B14: 8 | C14: indicatif HT
A15: Smartphones à remplacer | B15: 140 | C15: 135 Galaxy A5 + croissance
A16: Prix smartphone (Android Enterprise) | B16: 300
A17: Coût jour RSI chargé | B17: 450 | C17: coût interne
A18: Jours RSI sur le projet (8 mois) | B18: 80 | C18: ≈ 50 %
A19: Coût jour alternant chargé | B19: 150
A20: Jours alternant sur le projet | B20: 120
A21: Réserve de contingence (risques) | B21: 0.1 | C21: sur invest + charges
A22: Réserve de management | B22: 0.05
A23: Enveloppe budgétaire (Contexte SAP p.11) | B23: 800000

Sheet Investissement
A1: Lot | B1: Élément | C1: Quantité | D1: Prix unitaire HT | E1: Total HT | F1: Justification
A2: Postes | B2: Ordinateurs portables (renouvellement 100 %) | C2: =ROUNDUP(Hypothèses!$B$8*Hypothèses!$B$2*(1+Hypothèses!$B$3)*(1+Hypothèses!$B$4),0) | D2: =(Hypothèses!$B$5*(1-Hypothèses!$B$7)+Hypothèses!$B$6*Hypothèses!$B$7) | E2: =C2*D2 | F2: 450 ProBook 450 G2 de 2015 : non compatibles Windows 11, 300 HS ou à remplacer
A3: Postes | B3: Station d'accueil USB-C + écran 24" | C3: =Hypothèses!$B$10 | D3: 300 | E3: =C3*D3 | F3: postes administratifs sédentaires
A4: Postes | B4: Kit clavier/souris + sacoche | C4: =ROUNDUP(Hypothèses!$B$8*Hypothèses!$B$2*(1+Hypothèses!$B$3)*(1+Hypothèses!$B$4),0) | D4: 25 | E4: =C4*D4 | F4: 450 souris M185 dont 160 perdues
A5: Mobilité | B5: Smartphones Android Enterprise (gérés Intune) | C5: =Hypothèses!$B$15 | D5: =Hypothèses!$B$16 | E5: =C5*D5 | F5: 135 Galaxy A5 : 92 batterie faible ou écran cassé
A6: Réseau | B6: Pare-feu Lille (FortiGate 90G, HA) + UTP 3 ans | C6: 2 | D6: 5500 | E6: =C6*D6 | F6: hub siège, SD-WAN, VPN distants
A7: Réseau | B7: Pare-feu sites (FortiGate 70G, HA) + UTP 3 ans | C7: 8 | D7: 3500 | E7: =C7*D7 | F7: 2 par site x 4 sites, remplace Check Point 3200 + ASR 900
A8: Réseau | B8: Switchs cœur 10G (paire par site) | C8: 10 | D8: 3000 | E8: =C8*D8 | F8: remplace HP 5120, redondance cœur
A9: Réseau | B9: Switchs d'accès 48 ports PoE+ (1 par étage) | C9: 14 | D9: 2600 | E9: =C9*D9 | F9: 14 étages au total (plans des sites)
A10: Réseau | B10: Bornes Wi-Fi 6/6E + licences 3 ans | C10: 76 | D10: 600 | E10: =C10*D10 | F10: ≈ 1 borne / 200 m² (Lille 15, Lyon 9, Marseille 18, Paris 10, Toulouse 24)
A11: Réseau | B11: Onduleurs 3 kVA (2 par site) | C11: 10 | D11: 1500 | E11: =C11*D11 | F11: autonomie baies réseau
A12: Réseau | B12: Remise à niveau câblage Cat6A / brassage | C12: 5 | D12: 5000 | E12: =C12*D12 | F12: prises bornes Wi-Fi, baies d'étage
A13: Serveurs (Lille) | B13: Serveurs 1U (2 nœuds cluster Proxmox / Hyper-V) | C13: 2 | D13: 9000 | E13: =C13*D13 | F13: services locaux siège : DC, impression, cache, supervision
A14: Serveurs (Lille) | B14: NAS de sauvegarde (1er niveau, immuable) | C14: 1 | D14: 6000 | E14: =C14*D14 | F14: remplace LTO6 + ML110 G7
A15: Serveurs (Lille) | B15: Licences Windows Server 2025 Standard 16 cœurs | C15: 2 | D15: 1200 | E15: =C15*D15
A16: Prestations | B16: Audit Wi-Fi (site survey) 5 sites | C16: 5 | D16: 1000 | E16: =C16*D16
A17: Prestations | B17: Intégration cloud HDS + migration Exchange 2010 vers M365 | C17: 1 | D17: 20000 | E17: =C17*D17
A18: Prestations | B18: Migration données ERP vers solution SaaS HDS | C18: 1 | D18: 20000 | E18: =C18*D18 | F18: reprise PostgreSQL / Debian 7
A19: Accompagnement | B19: Formation et sensibilisation utilisateurs | C19: 1 | D19: 15000 | E19: =C19*D19 | F19: profils non technophiles
A20: GreenIT | B20: Effacement certifié + recyclage DEEE (ESS) des anciens postes | C20: 450 | D20: 10 | E20: =C20*D20 | F20: reconditionnement par entreprise adaptée
B21: TOTAL INVESTISSEMENT | E21: =SUM(E2:E20)

Sheet Charges an 1
A1: Poste | B1: Élément | C1: Quantité | D1: Coût mensuel HT | E1: Total annuel HT | F1: Justification
A2: Licences | B2: Microsoft 365 E3 | C2: =Hypothèses!$B$11 | D2: =Hypothèses!$B$13 | E2: =C2*D2*12 | F2: messagerie, Teams, SharePoint (GED), Intune ; Microsoft certifié HDS
A3: Licences | B3: Microsoft 365 F3 | C3: =Hypothèses!$B$12 | D3: =Hypothèses!$B$14 | E3: =C3*D3*12 | F3: profils terrain en mobilité
A4: Cloud HDS | B4: IaaS hébergeur certifié HDS (région principale) | C4: 1 | D4: 2500 | E4: =C4*D4*12 | F4: AD, fichiers, GLPI, supervision, bastion
A5: Cloud HDS | B5: Sauvegarde externalisée + réplication PRA (2e région) | C5: 1 | D5: 800 | E5: =C5*D5*12 | F5: règle 3-2-1, datacenter labellisé GreenIT
A6: Cloud HDS | B6: ERP médico-social SaaS HDS (indicatif) | C6: =450*Hypothèses!$B$9 | D6: 12 | E6: =C6*D6*12 | F6: à affiner avec les éditeurs ; peut relever du budget métier
A7: Liens | B7: Fibre dédiée FTTO 1 Gb/s par site | C7: 5 | D7: 500 | E7: =C7*D7*12 | F7: lien principal
A8: Liens | B8: Lien de secours (FTTH pro ou 4G/5G) | C8: 5 | D8: 70 | E8: =C8*D8*12 | F8: bascule SD-WAN, dispo 99,9 %
A9: Logiciels | B9: Sauvegarde (Veeam ou équivalent) | C9: 1 | D9: 250 | E9: =C9*D9*12
A10: Logiciels | B10: Support Proxmox / maintenance serveurs | C10: 1 | D10: 150 | E10: =C10*D10*12
B11: TOTAL CHARGES ANNUELLES | E11: =SUM(E2:E10)
